fclist.py
setup.py
fclist.egg-info/PKG-INFO
fclist.egg-info/SOURCES.txt
fclist.egg-info/dependency_links.txt
fclist.egg-info/not-zip-safe
fclist.egg-info/requires.txt
fclist.egg-info/top_level.txt