Metadata-Version: 1.1
Name: fclist
Version: 1.1.1
Summary: ("Python cffi bridge to fontconfig's FcFontList/FcFontMatch",)
Home-page: http://github.com/tarruda/python-fclist
Author: Thiago de Arruda
Author-email: tpadilha84@gmail.com
License: MIT
Download-URL: https://github.com/tarruda/python-fclist/archive/1.1.1.tar.gz
Platform: UNKNOWN
